django_policies/__init__.py
django_policies/apps.py
django_policies/backends.py
django_policies/decorators.py
django_policies/mixins.py
django_policies/policies.py
django_policies/registry.py
django_policies/templatetags/__init__.py
django_policies/templatetags/policies.py
django_policies-0.3.dist-info/METADATA
django_policies-0.3.dist-info/WHEEL
django_policies-0.3.dist-info/licenses/LICENSE
django_policies-0.3.dist-info/RECORD
