Metadata-Version: 2.4
Name: django-policies
Version: 0.3
Project-URL: Homepage, https://github.com/gardenerik/django-policies/
Author-email: Adam Zahradník <adam@zahradnik.xyz>
License-Expression: MIT
License-File: LICENSE
Classifier: Development Status :: 4 - Beta
Classifier: Environment :: Web Environment
Classifier: Framework :: Django
Classifier: License :: OSI Approved :: MIT License
Requires-Python: >=3.10
Requires-Dist: django>=5.0.0
